hack4u/__init__.py
hack4u/courses.py
hack4u/utils.py
crazy4hack-0.5.1.dist-info/METADATA
crazy4hack-0.5.1.dist-info/WHEEL
crazy4hack-0.5.1.dist-info/top_level.txt
crazy4hack-0.5.1.dist-info/RECORD
